prodigy_plus_schedule_free-2.0.1.dist-info/licenses/LICENSE
prodigyplus/__init__.py
prodigyplus/core_optimiser.py
prodigyplus/prodigy_plus_schedulefree.py
prodigy_plus_schedule_free-2.0.1.dist-info/METADATA
prodigy_plus_schedule_free-2.0.1.dist-info/WHEEL
prodigy_plus_schedule_free-2.0.1.dist-info/top_level.txt
prodigy_plus_schedule_free-2.0.1.dist-info/RECORD
