Metadata-Version: 2.4
Name: prodigy-plus-schedule-free
Version: 2.0.1
Summary: Automatic learning rate optimiser based on Prodigy and Schedule-Free
Home-page: https://github.com/LoganBooker/prodigy-plus-schedule-free
Author: Logan Booker
Author-email: me@loganbooker.dev
License: Apache-2.0
Keywords: artificial intelligence,deep learning,optimizers
Classifier: Programming Language :: Python :: 3
Classifier: Operating System :: OS Independent
Requires-Python: >=3.4
License-File: LICENSE
Requires-Dist: torch>=2.0
Dynamic: author
Dynamic: author-email
Dynamic: classifier
Dynamic: description
Dynamic: description-content-type
Dynamic: home-page
Dynamic: keywords
Dynamic: license
Dynamic: license-file
Dynamic: requires-dist
Dynamic: requires-python
Dynamic: summary
